tlg_indices/__init__.py
tlg_indices/data_types.py
tlg_indices/file_utils.py
tlg_indices/phi5_index_utils.py
tlg_indices/py.typed
tlg_indices/text_cleaning.py
tlg_indices/tlg_index_utils.py
tlg_indices/tlgu.py
tlg_indices/indices/__init__.py
tlg_indices/indices/author_id_to_author_name.py
tlg_indices/indices/author_id_to_name.py
tlg_indices/indices/author_ids_to_works.py
tlg_indices/indices/date_to_author_id.py
tlg_indices/indices/epithet_to_author_id.py
tlg_indices/indices/female_author_ids.py
tlg_indices/indices/geography_to_author_id.py
tlg_indices/indices/phi5_author_id_to_name.py
tlg_indices/indices/phi5_author_id_to_works.py
tlg_indices/indices/tlg_indices.py
tlg_indices-1.4.2.dist-info/METADATA
tlg_indices-1.4.2.dist-info/WHEEL
tlg_indices-1.4.2.dist-info/RECORD
