Metadata-Version: 2.4
Name: tlg-indices
Version: 1.4.2
Summary: Browse TLG indices
Project-URL: Repository, https://github.com/cltk/tlg_indices
Requires-Python: >=3.13
